scintillant/__init__.py
scintillant/entry_points.py
scintillant/apimodels/__init__.py
scintillant/apimodels/types.py
scintillant/commands/__init__.py
scintillant/commands/templates.py
scintillant/commands/testserver.py
scintillant/commands/testsuite.py
scintillant/commands/utils.py
scintillant/controllers/__init__.py
scintillant/controllers/context_controller.py
scintillant/textutils/__init__.py
scintillant/textutils/phrase.py
scintillant/textutils/phrase_generator.py
scintillant/textutils/random_phrase.py
scintillant/textutils/random_sentence.py
scintillant-1.0.5.dist-info/LICENSE
scintillant-1.0.5.dist-info/METADATA
scintillant-1.0.5.dist-info/WHEEL
scintillant-1.0.5.dist-info/entry_points.txt
scintillant-1.0.5.dist-info/top_level.txt
scintillant-1.0.5.dist-info/RECORD
