Metadata-Version: 2.1
Name: scintillant
Version: 1.0.5
Summary: Fast bot creating framework
Home-page: https://code.tatar.ru/projects/LILIYA/repos/scintillant
Author: Niel Ketov
Author-email: ketov-x@yandex.ru
License: Apache 2.0
Keywords: package development template
Platform: UNKNOWN
Requires-Python: >=3.9.*,>=3.10.*
License-File: LICENSE
Requires-Dist: tqdm
Requires-Dist: requests
Requires-Dist: livereload
Requires-Dist: Click
Requires-Dist: pydantic
